{
  "name": "Cyprus",
  "cities": [
    {
      "name": "Ayia Napa",
      "interests": [
        {
          "name": "Nissi Beach",
          "map_link": "https://www.google.com/maps/search/?api=1&query=34.9896%2C33.9682",
          "description": "Famous sandy beach with shallow turquoise water and a small islet reachable by foot in calm conditions."
        },
        {
          "name": "Ayia Napa Monastery",
          "map_link": "https://www.google.com/maps/search/?api=1&query=34.9899%2C33.9992",
          "description": "Historic medieval monastery located in the town center, offering a quiet contrast to the beach scene."
        },
        {
          "name": "Cape Greco National Forest Park",
          "map_link": "https://www.google.com/maps/search/?api=1&query=34.9640%2C34.0760",
          "description": "Protected natural area with sea cliffs, hiking trails, caves, and panoramic viewpoints."
        },
        {
          "name": "Fig Tree Bay",
          "map_link": "https://www.google.com/maps/search/?api=1&query=35.0129%2C34.0586",
          "description": "Popular nearby beach in Protaras known for calm waters and soft sand."
        },
        {
          "name": "Ayia Napa Harbour",
          "map_link": "https://www.google.com/maps/search/?api=1&query=34.9868%2C34.0034",
          "description": "Small harbor area with walking paths, cafés, and boat excursions."
        }
      ],
      "local_food_tip": "Try Cypriot dishes such as souvlaki, halloumi cheese, meze, fresh seafood, and loukoumades. Taverns near the harbor are good for traditional meals.",
      "full_day": {
        "Morning": "Start your day at <a href=\"https://www.google.com/maps/search/?api=1&query=34.9896%2C33.9682\" target=\"_blank\" rel=\"noopener\">Nissi Beach</a> ☀️ for swimming and relaxing by the sea.",
        "Afternoon": "Have lunch near the harbor 🍽️ and visit the <a href=\"https://www.google.com/maps/search/?api=1&query=34.9899%2C33.9992\" target=\"_blank\" rel=\"noopener\">Ayia Napa Monastery</a> 🏛️ for a short cultural break.",
        "Sunset": "Head to <a href=\"https://www.google.com/maps/search/?api=1&query=34.9640%2C34.0760\" target=\"_blank\" rel=\"noopener\">Cape Greco</a> 🌅 to enjoy cliffs, sea views, and sunset colors.",
        "Night": "Evening walk around <a href=\"https://www.google.com/maps/search/?api=1&query=34.9868%2C34.0034\" target=\"_blank\" rel=\"noopener\">Ayia Napa Harbour</a> ✨ with dinner by the water."
      },
      "seasons": {
        "spring": {
          "event": "Spring Coastal Season",
          "description": "Warm but comfortable weather with blooming nature around Cape Greco.",
          "ideas": [
            {
              "name": "Hiking Cape Greco trails",
              "map_link": "https://www.google.com/maps/search/?api=1&query=34.9640%2C34.0760",
              "description": "Ideal temperatures for outdoor exploration."
            },
            {
              "name": "Beach walks",
              "map_link": "https://www.google.com/maps/search/?api=1&query=34.9896%2C33.9682",
              "description": "Quiet beaches before peak season."
            },
            {
              "name": "Monastery visit",
              "map_link": "https://www.google.com/maps/search/?api=1&query=34.9899%2C33.9992",
              "description": "Peaceful cultural stop."
            }
          ]
        },
        "summer": {
          "event": "Ayia Napa Summer Season",
          "description": "Hot weather, lively atmosphere, and full beach life.",
          "ideas": [
            {
              "name": "Swimming and snorkeling",
              "map_link": "https://www.google.com/maps/search/?api=1&query=34.9896%2C33.9682",
              "description": "Clear and warm sea conditions."
            },
            {
              "name": "Boat trips",
              "map_link": "https://www.google.com/maps/search/?api=1&query=34.9868%2C34.0034",
              "description": "Coastal sightseeing and sea caves."
            },
            {
              "name": "Evening seaside walks",
              "map_link": "https://www.google.com/maps/search/?api=1&query=34.9868%2C34.0034",
              "description": "Lively summer evenings."
            }
          ]
        },
        "autumn": {
          "event": "Golden Mediterranean Autumn",
          "description": "Warm sea, fewer crowds, and relaxed pace.",
          "ideas": [
            {
              "name": "Beach relaxation",
              "map_link": "https://www.google.com/maps/search/?api=1&query=35.0129%2C34.0586",
              "description": "Comfortable water temperatures."
            },
            {
              "name": "Photography at Cape Greco",
              "map_link": "https://www.google.com/maps/search/?api=1&query=34.9640%2C34.0760",
              "description": "Soft autumn light."
            },
            {
              "name": "Local taverns",
              "map_link": "https://www.google.com/maps/search/?api=1&query=34.9875%2C34.0010",
              "description": "Seasonal Cypriot cuisine."
            }
          ]
        },
        "winter": {
          "event": "Quiet Coastal Winter",
          "description": "Mild winters with calm streets and nature-focused visits.",
          "ideas": [
            {
              "name": "Coastal walks",
              "map_link": "https://www.google.com/maps/search/?api=1&query=34.9640%2C34.0760",
              "description": "Fresh air and sea views."
            },
            {
              "name": "Cultural visits",
              "map_link": "https://www.google.com/maps/search/?api=1&query=34.9899%2C33.9992",
              "description": "Uncrowded historical sites."
            },
            {
              "name": "Harbor cafés",
              "map_link": "https://www.google.com/maps/search/?api=1&query=34.9868%2C34.0034",
              "description": "Relaxed local atmosphere."
            }
          ]
        }
      },
      "public_transport_tips": [
        {
          "tip": "Local buses connect Ayia Napa with Protaras and Cape Greco.",
          "link": "https://osea.com.cy/"
        },
        {
          "tip": "Walking is practical within the town center and beach areas.",
          "link": "https://www.visitcyprus.com/"
        },
        {
          "tip": "Larnaca Airport is the main international gateway, about 45 minutes away.",
          "link": "https://larnakaairport.com/"
        }
      ],
      "city_events": [
        {
          "name": "Ayia Napa International Festival",
          "season": "summer",
          "description": "Cultural festival featuring music, dance, and Cypriot traditions.",
          "website": "https://www.agianapa.org.cy/",
          "dates": "September"
        }
      ],
      "places": [
        {
          "name": "Thalassa Municipal Museum",
          "map_link": "https://www.google.com/maps/search/?api=1&query=34.9904%2C33.9998",
          "description": "Museum dedicated to the maritime history of Cyprus."
        },
        {
          "name": "Makronissos Tombs",
          "map_link": "https://www.google.com/maps/search/?api=1&query=34.9827%2C33.9577",
          "description": "Ancient Hellenistic and Roman tombs near the coast."
        }
      ],
      "hidden_gems": [
        {
          "name": "Early-morning Nissi Beach",
          "map_link": "https://www.google.com/maps/search/?api=1&query=34.9896%2C33.9682",
          "description": "Calm water and quiet atmosphere before crowds arrive."
        },
        {
          "name": "Sea caves of Cape Greco",
          "map_link": "https://www.google.com/maps/search/?api=1&query=34.9658%2C34.0735",
          "description": "Dramatic coastal formations away from main beaches."
        }
      ]
    },

    {
      "name": "Larnaca",
      "interests": [
        {
          "name": "Finikoudes Promenade",
          "map_link": "https://www.google.com/maps/search/?api=1&query=34.9149%2C33.6363",
          "description": "Palm-lined seaside promenade with cafés, restaurants, and direct access to the main city beach."
        },
        {
          "name": "Church of Saint Lazarus",
          "map_link": "https://www.google.com/maps/search/?api=1&query=34.9126%2C33.6356",
          "description": "9th-century Orthodox church built over the tomb of Saint Lazarus, one of Cyprus’ most important religious landmarks."
        },
        {
          "name": "Larnaca Salt Lake",
          "map_link": "https://www.google.com/maps/search/?api=1&query=34.8896%2C33.6306",
          "description": "Large salt lake famous for winter flamingos and scenic walking paths."
        },
        {
          "name": "Hala Sultan Tekke",
          "map_link": "https://www.google.com/maps/search/?api=1&query=34.8890%2C33.6235",
          "description": "Important Islamic shrine located beside the Salt Lake, surrounded by palm trees and calm scenery."
        },
        {
          "name": "Mackenzie Beach",
          "map_link": "https://www.google.com/maps/search/?api=1&query=34.9008%2C33.6330",
          "description": "Popular sandy beach close to the airport, known for beach bars and plane-spotting views."
        }
      ],
      "local_food_tip": "Try Cypriot meze, grilled halloumi, souvlaki, fresh seafood, and traditional desserts like loukoumades. Finikoudes and Mackenzie areas have many reliable taverns.",
      "full_day": {
        "Morning": "Start with a seaside walk along <a href=\"https://www.google.com/maps/search/?api=1&query=34.9149%2C33.6363\" target=\"_blank\" rel=\"noopener\">Finikoudes Promenade</a> ☀️ and breakfast by the sea.",
        "Afternoon": "Visit the <a href=\"https://www.google.com/maps/search/?api=1&query=34.9126%2C33.6356\" target=\"_blank\" rel=\"noopener\">Church of Saint Lazarus</a> ⛪, then head to <a href=\"https://www.google.com/maps/search/?api=1&query=34.9008%2C33.6330\" target=\"_blank\" rel=\"noopener\">Mackenzie Beach</a> 🏖️ for swimming and lunch.",
        "Sunset": "Walk around <a href=\"https://www.google.com/maps/search/?api=1&query=34.8896%2C33.6306\" target=\"_blank\" rel=\"noopener\">Larnaca Salt Lake</a> 🌅 and stop by <a href=\"https://www.google.com/maps/search/?api=1&query=34.8890%2C33.6235\" target=\"_blank\" rel=\"noopener\">Hala Sultan Tekke</a>.",
        "Night": "Dinner at Mackenzie or Finikoudes ✨ with relaxed seaside atmosphere."
      },
      "seasons": {
        "spring": {
          "event": "Spring Coastal Season",
          "description": "Warm temperatures and blooming nature around the Salt Lake.",
          "ideas": [
            {
              "name": "Salt Lake walks",
              "map_link": "https://www.google.com/maps/search/?api=1&query=34.8896%2C33.6306",
              "description": "Mild weather and open landscapes."
            },
            {
              "name": "Old town strolls",
              "map_link": "https://www.google.com/maps/search/?api=1&query=34.9126%2C33.6356",
              "description": "Comfortable sightseeing."
            },
            {
              "name": "Beach walks",
              "map_link": "https://www.google.com/maps/search/?api=1&query=34.9149%2C33.6363",
              "description": "Quiet seaside mornings."
            }
          ]
        },
        "summer": {
          "event": "Larnaca Summer Festival",
          "description": "Beach life, open-air events, and lively evenings.",
          "ideas": [
            {
              "name": "Swimming at Mackenzie",
              "map_link": "https://www.google.com/maps/search/?api=1&query=34.9008%2C33.6330",
              "description": "Clear water and beach bars."
            },
            {
              "name": "Evening promenade walks",
              "map_link": "https://www.google.com/maps/search/?api=1&query=34.9149%2C33.6363",
              "description": "Lively summer nights."
            },
            {
              "name": "Boat trips",
              "map_link": "https://www.google.com/maps/search/?api=1&query=34.9155%2C33.6370",
              "description": "Short coastal excursions."
            }
          ]
        },
        "autumn": {
          "event": "Golden Mediterranean Autumn",
          "description": "Warm sea and fewer visitors.",
          "ideas": [
            {
              "name": "Beach relaxation",
              "map_link": "https://www.google.com/maps/search/?api=1&query=34.9149%2C33.6363",
              "description": "Comfortable sea temperatures."
            },
            {
              "name": "Cultural visits",
              "map_link": "https://www.google.com/maps/search/?api=1&query=34.9126%2C33.6356",
              "description": "Quiet historic sites."
            },
            {
              "name": "Photography at Salt Lake",
              "map_link": "https://www.google.com/maps/search/?api=1&query=34.8896%2C33.6306",
              "description": "Soft autumn light."
            }
          ]
        },
        "winter": {
          "event": "Flamingo Season",
          "description": "Migratory flamingos gather at the Salt Lake.",
          "ideas": [
            {
              "name": "Birdwatching",
              "map_link": "https://www.google.com/maps/search/?api=1&query=34.8896%2C33.6306",
              "description": "Seasonal wildlife experience."
            },
            {
              "name": "Museum visits",
              "map_link": "https://www.google.com/maps/search/?api=1&query=34.9132%2C33.6360",
              "description": "Indoor cultural time."
            },
            {
              "name": "Café culture",
              "map_link": "https://www.google.com/maps/search/?api=1&query=34.9149%2C33.6363",
              "description": "Relaxed winter atmosphere."
            }
          ]
        }
      },
      "public_transport_tips": [
        {
          "tip": "Local buses connect beaches, the city center, and the airport.",
          "link": "https://osea.com.cy/"
        },
        {
          "tip": "Larnaca is compact and walkable along the seafront.",
          "link": "https://www.visitcyprus.com/"
        },
        {
          "tip": "Larnaca International Airport is located just south of the city.",
          "link": "https://larnakaairport.com/"
        }
      ],
      "city_events": [
        {
          "name": "Kataklysmos (Festival of the Flood)",
          "season": "summer",
          "description": "Traditional Cypriot festival with music, food, and cultural events by the sea.",
          "website": "https://www.visitcyprus.com/",
          "dates": "May–June (varies)"
        }
      ],
      "places": [
        {
          "name": "Pierides Archaeological Museum",
          "map_link": "https://www.google.com/maps/search/?api=1&query=34.9153%2C33.6368",
          "description": "Small museum showcasing Cypriot archaeology from prehistoric to medieval times."
        },
        {
          "name": "Larnaca Marina",
          "map_link": "https://www.google.com/maps/search/?api=1&query=34.9164%2C33.6375",
          "description": "Pleasant marina area near Finikoudes with boats and cafés."
        }
      ],
      "hidden_gems": [
        {
          "name": "Early-morning Finikoudes",
          "map_link": "https://www.google.com/maps/search/?api=1&query=34.9149%2C33.6363",
          "description": "Peaceful promenade before the city wakes up."
        },
        {
          "name": "Quiet paths near Hala Sultan Tekke",
          "map_link": "https://www.google.com/maps/search/?api=1&query=34.8890%2C33.6235",
          "description": "Calm nature and reflective scenery."
        }
      ]
    },

    {
      "name": "Limassol",
      "interests": [
        {
          "name": "Limassol Marina",
          "map_link": "https://www.google.com/maps/search/?api=1&query=34.6709%2C33.0416",
          "description": "Modern marina with yachts, seaside restaurants, cafés, and a lively promenade popular day and night."
        },
        {
          "name": "Limassol Old Town",
          "map_link": "https://www.google.com/maps/search/?api=1&query=34.6732%2C33.0438",
          "description": "Historic center with narrow streets, traditional shops, local taverns, and cultural landmarks."
        },
        {
          "name": "Limassol Castle",
          "map_link": "https://www.google.com/maps/search/?api=1&query=34.6737%2C33.0430",
          "description": "Medieval castle housing the Cyprus Medieval Museum, located in the heart of the Old Town."
        },
        {
          "name": "Molossia Promenade",
          "map_link": "https://www.google.com/maps/search/?api=1&query=34.6840%2C33.0555",
          "description": "Long palm-lined coastal promenade ideal for walking, cycling, and sea views."
        },
        {
          "name": "Kourion Archaeological Site",
          "map_link": "https://www.google.com/maps/search/?api=1&query=34.6646%2C32.8887",
          "description": "Ancient Greco-Roman city with a spectacular cliffside theatre overlooking the Mediterranean."
        }
      ],
      "local_food_tip": "Try Cypriot meze, souvlaki, grilled halloumi, fresh seafood, and local wines from nearby Troodos foothills. Old Town taverns offer authentic flavors.",
      "full_day": {
        "Morning": "Start with coffee at <a href=\"https://www.google.com/maps/search/?api=1&query=34.6709%2C33.0416\" target=\"_blank\" rel=\"noopener\">Limassol Marina</a> ☀️, then walk into the <a href=\"https://www.google.com/maps/search/?api=1&query=34.6732%2C33.0438\" target=\"_blank\" rel=\"noopener\">Old Town</a>.",
        "Afternoon": "Visit <a href=\"https://www.google.com/maps/search/?api=1&query=34.6737%2C33.0430\" target=\"_blank\" rel=\"noopener\">Limassol Castle</a> 🏛️ and enjoy lunch nearby 🍽️, followed by a stroll along the <a href=\"https://www.google.com/maps/search/?api=1&query=34.6840%2C33.0555\" target=\"_blank\" rel=\"noopener\">Molossia Promenade</a>.",
        "Sunset": "Take a short trip to <a href=\"https://www.google.com/maps/search/?api=1&query=34.6646%2C32.8887\" target=\"_blank\" rel=\"noopener\">Kourion</a> 🌅 for dramatic sunset views over the sea.",
        "Night": "Dinner at the marina ✨ or in the Old Town with relaxed nightlife and seaside ambiance."
      },
      "seasons": {
        "spring": {
          "event": "Spring Coastal Season",
          "description": "Comfortable temperatures and blooming landscapes make sightseeing ideal.",
          "ideas": [
            {
              "name": "Old Town walks",
              "map_link": "https://www.google.com/maps/search/?api=1&query=34.6732%2C33.0438",
              "description": "Pleasant weather for exploration."
            },
            {
              "name": "Promenade strolls",
              "map_link": "https://www.google.com/maps/search/?api=1&query=34.6840%2C33.0555",
              "description": "Fresh sea air and views."
            },
            {
              "name": "Kourion visit",
              "map_link": "https://www.google.com/maps/search/?api=1&query=34.6646%2C32.8887",
              "description": "Clear spring skies over ancient ruins."
            }
          ]
        },
        "summer": {
          "event": "Limassol Summer Festival Season",
          "description": "Hot weather, beach life, and open-air events across the city.",
          "ideas": [
            {
              "name": "Beach time",
              "map_link": "https://www.google.com/maps/search/?api=1&query=34.6890%2C33.0720",
              "description": "Swimming and sunbathing."
            },
            {
              "name": "Evening marina life",
              "map_link": "https://www.google.com/maps/search/?api=1&query=34.6709%2C33.0416",
              "description": "Lively summer nights."
            },
            {
              "name": "Coastal cycling",
              "map_link": "https://www.google.com/maps/search/?api=1&query=34.6840%2C33.0555",
              "description": "Long flat seaside routes."
            }
          ]
        },
        "autumn": {
          "event": "Wine & Harvest Season",
          "description": "Warm sea temperatures and wine activities in nearby villages.",
          "ideas": [
            {
              "name": "Wine village trips",
              "map_link": "https://www.google.com/maps/search/?api=1&query=34.8500%2C32.8000",
              "description": "Local wineries and harvest atmosphere."
            },
            {
              "name": "Photography walks",
              "map_link": "https://www.google.com/maps/search/?api=1&query=34.6646%2C32.8887",
              "description": "Golden light at ancient sites."
            },
            {
              "name": "Relaxed seaside dining",
              "map_link": "https://www.google.com/maps/search/?api=1&query=34.6709%2C33.0416",
              "description": "Calm coastal evenings."
            }
          ]
        },
        "winter": {
          "event": "Mild Mediterranean Winter",
          "description": "Quiet city life with mild temperatures and cultural focus.",
          "ideas": [
            {
              "name": "Museum visits",
              "map_link": "https://www.google.com/maps/search/?api=1&query=34.6737%2C33.0430",
              "description": "Indoor cultural exploration."
            },
            {
              "name": "Seafront walks",
              "map_link": "https://www.google.com/maps/search/?api=1&query=34.6840%2C33.0555",
              "description": "Peaceful winter scenery."
            },
            {
              "name": "Café culture",
              "map_link": "https://www.google.com/maps/search/?api=1&query=34.6732%2C33.0438",
              "description": "Relaxed local atmosphere."
            }
          ]
        }
      },
      "public_transport_tips": [
        {
          "tip": "Local buses connect Limassol Marina, Old Town, beaches, and suburbs.",
          "link": "https://www.limassolbuses.com/"
        },
        {
          "tip": "Walking and cycling are ideal along the long seafront promenade.",
          "link": "https://www.visitcyprus.com/"
        },
        {
          "tip": "Paphos and Larnaca airports are reachable by intercity buses.",
          "link": "https://intercity-buses.com/"
        }
      ],
      "city_events": [
        {
          "name": "Limassol Carnival",
          "season": "winter",
          "description": "Major cultural event with parades, costumes, and celebrations.",
          "website": "https://www.limassol.org.cy/",
          "dates": "February–March (varies)"
        }
      ],
      "places": [
        {
          "name": "Fasouri Watermania",
          "map_link": "https://www.google.com/maps/search/?api=1&query=34.6640%2C33.0128",
          "description": "Large water park popular with families and visitors during summer."
        },
        {
          "name": "Cyprus Motor Museum",
          "map_link": "https://www.google.com/maps/search/?api=1&query=34.7268%2C33.0045",
          "description": "Museum featuring a wide collection of classic and vintage cars."
        }
      ],
      "hidden_gems": [
        {
          "name": "Early-morning Molossia Promenade",
          "map_link": "https://www.google.com/maps/search/?api=1&query=34.6840%2C33.0555",
          "description": "Quiet sea views before the city becomes active."
        },
        {
          "name": "Backstreets of the Old Town",
          "map_link": "https://www.google.com/maps/search/?api=1&query=34.6728%2C33.0445",
          "description": "Authentic local life away from main streets."
        }
      ]
    },

    {
      "name": "Nicosia",
      "interests": [
        {
          "name": "Ledra Street Crossing",
          "map_link": "https://www.google.com/maps/search/?api=1&query=35.1686%2C33.3600",
          "description": "Pedestrian street and official crossing point between the southern and northern parts of the city, symbolizing Nicosia’s divided history."
        },
        {
          "name": "Cyprus Museum",
          "map_link": "https://www.google.com/maps/search/?api=1&query=35.1721%2C33.3626",
          "description": "The largest archaeological museum in Cyprus, showcasing artifacts from prehistoric to Roman times."
        },
        {
          "name": "Leventis Municipal Museum",
          "map_link": "https://www.google.com/maps/search/?api=1&query=35.1679%2C33.3608",
          "description": "Museum dedicated to the history of Nicosia, located near the old town walls."
        },
        {
          "name": "Venetian Walls of Nicosia",
          "map_link": "https://www.google.com/maps/search/?api=1&query=35.1729%2C33.3609",
          "description": "16th-century circular fortifications surrounding the old city, built by the Venetians."
        },
        {
          "name": "Famagusta Gate",
          "map_link": "https://www.google.com/maps/search/?api=1&query=35.1700%2C33.3721",
          "description": "One of the three original gates of the Venetian walls, now used as a cultural venue."
        }
      ],
      "local_food_tip": "Try Cypriot meze, souvlaki, sheftalia, grilled halloumi, and traditional sweets. Old town taverns around Ledra and Onasagorou streets are popular with locals.",
      "full_day": {
        "Morning": "Start your day at the <a href=\"https://www.google.com/maps/search/?api=1&query=35.1721%2C33.3626\" target=\"_blank\" rel=\"noopener\">Cyprus Museum</a> ☀️ to understand the island’s ancient history.",
        "Afternoon": "Walk through the old city to <a href=\"https://www.google.com/maps/search/?api=1&query=35.1679%2C33.3608\" target=\"_blank\" rel=\"noopener\">Leventis Municipal Museum</a> 🏛️ and have lunch along <a href=\"https://www.google.com/maps/search/?api=1&query=35.1686%2C33.3600\" target=\"_blank\" rel=\"noopener\">Ledra Street</a> 🍽️.",
        "Sunset": "Stroll along sections of the <a href=\"https://www.google.com/maps/search/?api=1&query=35.1729%2C33.3609\" target=\"_blank\" rel=\"noopener\">Venetian Walls</a> 🌅 near <a href=\"https://www.google.com/maps/search/?api=1&query=35.1700%2C33.3721\" target=\"_blank\" rel=\"noopener\">Famagusta Gate</a>.",
        "Night": "Dinner in the old town ✨ and an evening walk around Onasagorou Street."
      },
      "seasons": {
        "spring": {
          "event": "Spring Cultural Season",
          "description": "Mild temperatures make walking the old city comfortable and pleasant.",
          "ideas": [
            {
              "name": "Old town walks",
              "map_link": "https://www.google.com/maps/search/?api=1&query=35.1686%2C33.3600",
              "description": "Ideal weather for exploring historic streets."
            },
            {
              "name": "Museum visits",
              "map_link": "https://www.google.com/maps/search/?api=1&query=35.1721%2C33.3626",
              "description": "Comfortable indoor sightseeing."
            },
            {
              "name": "Café terraces",
              "map_link": "https://www.google.com/maps/search/?api=1&query=35.1680%2C33.3595",
              "description": "Relaxed city atmosphere."
            }
          ]
        },
        "summer": {
          "event": "Nicosia Summer Nights",
          "description": "Hot days with lively evenings focused on cafés and cultural events.",
          "ideas": [
            {
              "name": "Evening walks",
              "map_link": "https://www.google.com/maps/search/?api=1&query=35.1686%2C33.3600",
              "description": "Cooler temperatures after sunset."
            },
            {
              "name": "Indoor museums",
              "map_link": "https://www.google.com/maps/search/?api=1&query=35.1679%2C33.3608",
              "description": "Air-conditioned cultural visits."
            },
            {
              "name": "Night cafés",
              "map_link": "https://www.google.com/maps/search/?api=1&query=35.1688%2C33.3612",
              "description": "Social local nightlife."
            }
          ]
        },
        "autumn": {
          "event": "Golden City Autumn",
          "description": "Warm days, fewer visitors, and relaxed urban life.",
          "ideas": [
            {
              "name": "Historic exploration",
              "map_link": "https://www.google.com/maps/search/?api=1&query=35.1700%2C33.3721",
              "description": "Pleasant temperatures for sightseeing."
            },
            {
              "name": "Local cuisine",
              "map_link": "https://www.google.com/maps/search/?api=1&query=35.1686%2C33.3600",
              "description": "Seasonal Cypriot dishes."
            },
            {
              "name": "Photography walks",
              "map_link": "https://www.google.com/maps/search/?api=1&query=35.1729%2C33.3609",
              "description": "Soft autumn light on stone walls."
            }
          ]
        },
        "winter": {
          "event": "Mild Capital Winter",
          "description": "Cool but comfortable weather with calm streets and cultural focus.",
          "ideas": [
            {
              "name": "Museum hopping",
              "map_link": "https://www.google.com/maps/search/?api=1&query=35.1721%2C33.3626",
              "description": "Indoor cultural time."
            },
            {
              "name": "Old town cafés",
              "map_link": "https://www.google.com/maps/search/?api=1&query=35.1680%2C33.3595",
              "description": "Cozy winter atmosphere."
            },
            {
              "name": "City walks",
              "map_link": "https://www.google.com/maps/search/?api=1&query=35.1679%2C33.3608",
              "description": "Quiet historic streets."
            }
          ]
        }
      },
      "public_transport_tips": [
        {
          "tip": "Local buses connect the old city with modern districts.",
          "link": "https://www.publictransport.com.cy/"
        },
        {
          "tip": "The old town within the Venetian walls is best explored on foot.",
          "link": "https://www.visitcyprus.com/"
        },
        {
          "tip": "Intercity buses connect Nicosia with Limassol, Larnaca, and Paphos.",
          "link": "https://intercity-buses.com/"
        }
      ],
      "city_events": [
        {
          "name": "Nicosia International Festival",
          "season": "autumn",
          "description": "Cultural festival featuring music, theater, and exhibitions.",
          "website": "https://www.nicosia.org.cy/",
          "dates": "September–October"
        }
      ],
      "places": [
        {
          "name": "Shacolas Tower Observatory",
          "map_link": "https://www.google.com/maps/search/?api=1&query=35.1683%2C33.3606",
          "description": "Observation deck offering panoramic views over Nicosia."
        },
        {
          "name": "Hadjigeorgakis Kornesios Mansion",
          "map_link": "https://www.google.com/maps/search/?api=1&query=35.1708%2C33.3650",
          "description": "18th-century mansion and ethnological museum."
        }
      ],
      "hidden_gems": [
        {
          "name": "Early-morning Ledra Street",
          "map_link": "https://www.google.com/maps/search/?api=1&query=35.1686%2C33.3600",
          "description": "Quiet atmosphere before shops open."
        },
        {
          "name": "Side streets near Famagusta Gate",
          "map_link": "https://www.google.com/maps/search/?api=1&query=35.1705%2C33.3715",
          "description": "Local neighborhoods with authentic character."
        }
      ]
    },

    {
      "name": "Paphos",
      "interests": [
        {
          "name": "Paphos Archaeological Park",
          "map_link": "https://www.google.com/maps/search/?api=1&query=34.7566%2C32.4064",
          "description": "UNESCO World Heritage site featuring Roman villas with well-preserved mosaics, ancient ruins, and an amphitheater."
        },
        {
          "name": "Paphos Harbour & Medieval Castle",
          "map_link": "https://www.google.com/maps/search/?api=1&query=34.7559%2C32.4079",
          "description": "Historic harbor area with a medieval fortress, promenade, cafés, and sea views."
        },
        {
          "name": "Tombs of the Kings",
          "map_link": "https://www.google.com/maps/search/?api=1&query=34.7755%2C32.4087",
          "description": "Impressive underground Hellenistic necropolis carved into rock, despite the name not actually royal tombs."
        },
        {
          "name": "Coral Bay",
          "map_link": "https://www.google.com/maps/search/?api=1&query=34.8567%2C32.3726",
          "description": "Popular sandy beach north of Paphos with calm waters, ideal for swimming."
        },
        {
          "name": "Aphrodite’s Rock (Petra tou Romiou)",
          "map_link": "https://www.google.com/maps/search/?api=1&query=34.6653%2C32.6271",
          "description": "Legendary sea stack believed to be the birthplace of Aphrodite, one of Cyprus’ most iconic natural landmarks."
        }
      ],
      "local_food_tip": "Try Cypriot meze, fresh seafood, souvlaki, grilled halloumi, and local desserts. Harbor-side taverns are great for sunset dining.",
      "full_day": {
        "Morning": "Start at the <a href=\"https://www.google.com/maps/search/?api=1&query=34.7566%2C32.4064\" target=\"_blank\" rel=\"noopener\">Paphos Archaeological Park</a> ☀️ to explore ancient mosaics and ruins.",
        "Afternoon": "Head to <a href=\"https://www.google.com/maps/search/?api=1&query=34.7559%2C32.4079\" target=\"_blank\" rel=\"noopener\">Paphos Harbour</a> 🏛️ for lunch, then visit the <a href=\"https://www.google.com/maps/search/?api=1&query=34.7755%2C32.4087\" target=\"_blank\" rel=\"noopener\">Tombs of the Kings</a>.",
        "Sunset": "Drive or bus to <a href=\"https://www.google.com/maps/search/?api=1&query=34.6653%2C32.6271\" target=\"_blank\" rel=\"noopener\">Aphrodite’s Rock</a> 🌅 for dramatic coastal sunset views.",
        "Night": "Dinner at the harbor ✨ followed by a relaxed seaside walk."
      },
      "seasons": {
        "spring": {
          "event": "Spring Cultural Season",
          "description": "Warm but comfortable weather ideal for archaeological exploration.",
          "ideas": [
            {
              "name": "Ancient site visits",
              "map_link": "https://www.google.com/maps/search/?api=1&query=34.7566%2C32.4064",
              "description": "Perfect temperatures for walking ruins."
            },
            {
              "name": "Coastal walks",
              "map_link": "https://www.google.com/maps/search/?api=1&query=34.7559%2C32.4079",
              "description": "Fresh sea air."
            },
            {
              "name": "Village trips",
              "map_link": "https://www.google.com/maps/search/?api=1&query=34.8340%2C32.7060",
              "description": "Spring greenery inland."
            }
          ]
        },
        "summer": {
          "event": "Paphos Summer Festival",
          "description": "Beach life, open-air events, and lively evenings.",
          "ideas": [
            {
              "name": "Beach time at Coral Bay",
              "map_link": "https://www.google.com/maps/search/?api=1&query=34.8567%2C32.3726",
              "description": "Clear water and sandy shore."
            },
            {
              "name": "Evening harbor walks",
              "map_link": "https://www.google.com/maps/search/?api=1&query=34.7559%2C32.4079",
              "description": "Warm Mediterranean nights."
            },
            {
              "name": "Boat excursions",
              "map_link": "https://www.google.com/maps/search/?api=1&query=34.7562%2C32.4085",
              "description": "Coastal sightseeing."
            }
          ]
        },
        "autumn": {
          "event": "Golden Mediterranean Autumn",
          "description": "Warm sea, fewer crowds, and soft light.",
          "ideas": [
            {
              "name": "Photography at Aphrodite’s Rock",
              "map_link": "https://www.google.com/maps/search/?api=1&query=34.6653%2C32.6271",
              "description": "Golden-hour coastal scenes."
            },
            {
              "name": "Historic exploration",
              "map_link": "https://www.google.com/maps/search/?api=1&query=34.7755%2C32.4087",
              "description": "Pleasant sightseeing temperatures."
            },
            {
              "name": "Seaside dining",
              "map_link": "https://www.google.com/maps/search/?api=1&query=34.7559%2C32.4079",
              "description": "Relaxed evenings by the water."
            }
          ]
        },
        "winter": {
          "event": "Mild Coastal Winter",
          "description": "Comfortable climate with calm streets and cultural focus.",
          "ideas": [
            {
              "name": "Museum and site visits",
              "map_link": "https://www.google.com/maps/search/?api=1&query=34.7566%2C32.4064",
              "description": "Crowd-free archaeology."
            },
            {
              "name": "Coastal walks",
              "map_link": "https://www.google.com/maps/search/?api=1&query=34.7559%2C32.4079",
              "description": "Quiet seaside scenery."
            },
            {
              "name": "Café culture",
              "map_link": "https://www.google.com/maps/search/?api=1&query=34.7560%2C32.4068",
              "description": "Relaxed local atmosphere."
            }
          ]
        }
      },
      "public_transport_tips": [
        {
          "tip": "Local buses connect the harbor, archaeological sites, and Coral Bay.",
          "link": "https://www.pafosbuses.com/"
        },
        {
          "tip": "Walking is practical around the harbor and old town areas.",
          "link": "https://www.visitcyprus.com/"
        },
        {
          "tip": "Paphos International Airport is close to the city center.",
          "link": "https://www.hermesairports.com/"
        }
      ],
      "city_events": [
        {
          "name": "Paphos Aphrodite Festival",
          "season": "summer",
          "description": "Open-air opera festival held near the medieval castle.",
          "website": "https://www.paphosaphroditefestival.com/",
          "dates": "September"
        }
      ],
      "places": [
        {
          "name": "Agia Solomoni Catacombs",
          "map_link": "https://www.google.com/maps/search/?api=1&query=34.7583%2C32.4048",
          "description": "Early Christian catacombs and chapel near the archaeological park."
        },
        {
          "name": "Paphos Lighthouse",
          "map_link": "https://www.google.com/maps/search/?api=1&query=34.7589%2C32.4017",
          "description": "Coastal lighthouse offering open views over the sea."
        }
      ],
      "hidden_gems": [
        {
          "name": "Early-morning harbor",
          "map_link": "https://www.google.com/maps/search/?api=1&query=34.7559%2C32.4079",
          "description": "Quiet reflections and fishing boats at dawn."
        },
        {
          "name": "Coastal paths near Lighthouse",
          "map_link": "https://www.google.com/maps/search/?api=1&query=34.7595%2C32.4008",
          "description": "Peaceful seaside walks away from crowds."
        }
      ]
    }

  ]
}